qslib/__init__.py
qslib/_analysis_protocol_text.py
qslib/_util.py
qslib/base.py
qslib/cli.py
qslib/common.py
qslib/data.py
qslib/experiment.py
qslib/machine.py
qslib/monitor.py
qslib/monitor_cli.py
qslib/plate_setup.py
qslib/processors.py
qslib/protocol.py
qslib/py.typed
qslib/qs_is_protocol.py
qslib/qsconnection_async.py
qslib/rawquant_compat.py
qslib/scpi_commands.py
qslib/version.py
qslib-1.8.2.dist-info/AUTHORS.md
qslib-1.8.2.dist-info/LICENSE.txt
qslib-1.8.2.dist-info/METADATA
qslib-1.8.2.dist-info/WHEEL
qslib-1.8.2.dist-info/entry_points.txt
qslib-1.8.2.dist-info/top_level.txt
qslib-1.8.2.dist-info/RECORD
