Metadata-Version: 2.1
Name: qslib
Version: 1.8.2
Summary: Library for communicating with and using the QuantStudio qPCR machine, intended for non-qPCR uses.
Home-page: https://github.com/cgevans/qslib/
Author: Constantine Evans
Author-email: Constantine Evans <const@costi.eu>
License: GNU AFFERO GENERAL PUBLIC LICENSE
Project-URL: homepage, https://github.com/cgevans/qslib/
Project-URL: documentation, https://qslib.readthedocs.org/
Project-URL: source, https://github.com/cgevans/qslib/
Project-URL: changelog, https://github.com/cgevans/qslib/blob/main/CHANGELOG.md
Project-URL: tracker, https://github.com/cgevans/qslib/issues
Project-URL: download, https://github.com/cgevans/qslib/releases
Platform: any
Classifier: Development Status :: 4 - Beta
Classifier: Programming Language :: Python
Classifier: Intended Audience :: Science/Research
Classifier: License :: OSI Approved :: GNU General Public License v3 (GPLv3)
Classifier: Natural Language :: English
Classifier: Topic :: Scientific/Engineering
Classifier: Topic :: Scientific/Engineering :: Chemistry
Classifier: Topic :: Scientific/Engineering :: Physics
Classifier: Typing :: Typed
Classifier: Programming Language :: Python :: 3.9
Classifier: Programming Language :: Python :: 3.10
Classifier: Programming Language :: Python :: 3.11
Classifier: Framework :: Matplotlib
Classifier: Framework :: Jupyter
Requires-Python: >=3.9
License-File: LICENSE.txt
License-File: AUTHORS.md
Requires-Dist: pandas (>=1)
Requires-Dist: numpy (>=1)
Requires-Dist: tabulate (>=0.8)
Requires-Dist: pyparsing (>=3)
Requires-Dist: typeguard (>=2)
Requires-Dist: nest-asyncio (>=1.5)
Requires-Dist: click (<9.0,>=8.0)
Requires-Dist: toml
Requires-Dist: pint
Requires-Dist: attrs
Requires-Dist: matplotlib
Requires-Dist: markdown
Requires-Dist: dacite
Provides-Extra: docs
Requires-Dist: myst-parser ; extra == 'docs'
Requires-Dist: influxdb-client ; extra == 'docs'
Requires-Dist: toml ; extra == 'docs'
Requires-Dist: lxml ; extra == 'docs'
Requires-Dist: sphinx-click ; extra == 'docs'
Requires-Dist: sphinx-autodoc-typehints ; extra == 'docs'
Provides-Extra: monitor
Requires-Dist: matrix-nio ; extra == 'monitor'
Requires-Dist: influxdb-client ; extra == 'monitor'
Requires-Dist: toml ; extra == 'monitor'
Requires-Dist: lxml ; extra == 'monitor'
Provides-Extra: testing
Requires-Dist: setuptools ; extra == 'testing'
Requires-Dist: pytest ; extra == 'testing'
Requires-Dist: pytest-cov ; extra == 'testing'
Requires-Dist: pytest-asyncio ; extra == 'testing'
Requires-Dist: hypothesis ; extra == 'testing'
